talar/__init__.py
talar/client/__init__.py
talar/client/auth.py
talar/main.py
talar/resources/__init__.py
talar/resources/abstract.py
talar/resources/api_keys.py
talar/resources/currency_conversions.py
talar/resources/projects.py
talar/resources/tests/__init__.py
talar/resources/tests/test_integrations.py
talar/version.py
talar-0.2.0.dist-info/LICENSE
talar-0.2.0.dist-info/WHEEL
talar-0.2.0.dist-info/METADATA
talar-0.2.0.dist-info/RECORD
