Metadata-Version: 2.1
Name: talar
Version: 0.2.0
Summary: Python library for the Talar API
License: MIT
Author: Your Name
Author-email: you@example.com
Requires-Python: >=3.6,<4.0
Classifier: License :: OSI Approved :: MIT License
Classifier: Programming Language :: Python :: 3
Classifier: Programming Language :: Python :: 3.6
Classifier: Programming Language :: Python :: 3.7
Classifier: Programming Language :: Python :: 3.8
Classifier: Programming Language :: Python :: 3.9
Requires-Dist: pydantic (>=1.7.3,<2.0.0)
Requires-Dist: requests (>=2.25.1,<3.0.0)
Requires-Dist: typing-extensions (>=3.7.4,<4.0.0)
